[
  {
    "retailerSlug": "beaches_apparel",
    "retailerName": "Beaches Apparel",
    "website": "https://beachesapparel.com",
    "platform": "woocommerce",
    "regionCode": "AU",
    "enabled": false,
    "governanceStatus": "business_disabled",
    "governanceReason": "Clothing/apparel store, not suitable for Quivrr hardboard retailer inventory",
    "approvedLogoFile": "",
    "logoPath": "",
    "availableInventory": 0,
    "verifiedSurfboards": 0,
    "rawProducts": 5
  },
  {
    "retailerSlug": "ocean_and_earth",
    "retailerName": "Ocean and Earth",
    "website": "https://oceanearthstore.com",
    "platform": "magento",
    "regionCode": "AU",
    "enabled": false,
    "governanceStatus": "business_disabled",
    "governanceReason": "Brand/accessory store, not suitable for Quivrr hardboard retailer inventory",
    "approvedLogoFile": "",
    "logoPath": "",
    "availableInventory": 0,
    "verifiedSurfboards": 0,
    "rawProducts": 0
  },
  {
    "retailerSlug": "rip_curl_australia",
    "retailerName": "Rip Curl Australia",
    "website": "https://ripcurl.com",
    "platform": "magento",
    "regionCode": "AU",
    "enabled": false,
    "governanceStatus": "business_disabled",
    "governanceReason": "Does not sell hardboard surfboard inventory online for Quivrr search",
    "approvedLogoFile": "",
    "logoPath": "",
    "availableInventory": 0,
    "verifiedSurfboards": 0,
    "rawProducts": 0
  },
  {
    "retailerSlug": "board_hub",
    "retailerName": "Board Hub",
    "website": "https://boardhub.com.au",
    "platform": "woocommerce",
    "regionCode": "AU",
    "enabled": false,
    "governanceStatus": "endpoint_review",
    "governanceReason": "No raw products returned from scrape output",
    "approvedLogoFile": "",
    "logoPath": "",
    "availableInventory": 0,
    "verifiedSurfboards": 0,
    "rawProducts": 0
  },
  {
    "retailerSlug": "board_store",
    "retailerName": "Board Store",
    "website": "https://boardstore.com.au",
    "platform": "neto_maropost",
    "regionCode": "AU",
    "enabled": false,
    "governanceStatus": "endpoint_review",
    "governanceReason": "No raw products returned from scrape output",
    "approvedLogoFile": "",
    "logoPath": "",
    "availableInventory": 0,
    "verifiedSurfboards": 0,
    "rawProducts": 0
  },
  {
    "retailerSlug": "boardriders_coolangatta",
    "retailerName": "Boardriders Coolangatta",
    "website": "https://boardriders.co",
    "platform": "woocommerce",
    "regionCode": "AU",
    "enabled": false,
    "governanceStatus": "endpoint_review",
    "governanceReason": "No raw products returned from scrape output",
    "approvedLogoFile": "",
    "logoPath": "",
    "availableInventory": 0,
    "verifiedSurfboards": 0,
    "rawProducts": 0
  },
  {
    "retailerSlug": "full_circle_surf",
    "retailerName": "Full Circle Surf",
    "website": "https://fullcirclesurf.com.au",
    "platform": "squarespace",
    "regionCode": "AU",
    "enabled": false,
    "governanceStatus": "endpoint_review",
    "governanceReason": "No raw products returned from scrape output",
    "approvedLogoFile": "",
    "logoPath": "",
    "availableInventory": 0,
    "verifiedSurfboards": 0,
    "rawProducts": 0
  },
  {
    "retailerSlug": "goodtime_surfboards",
    "retailerName": "Goodtime Surfboards",
    "website": "https://goodtime.com.au",
    "platform": "magento",
    "regionCode": "AU",
    "enabled": false,
    "governanceStatus": "endpoint_review",
    "governanceReason": "No raw products returned from scrape output",
    "approvedLogoFile": "",
    "logoPath": "",
    "availableInventory": 0,
    "verifiedSurfboards": 0,
    "rawProducts": 0
  },
  {
    "retailerSlug": "mid_coast_surf",
    "retailerName": "Mid Coast Surf",
    "website": "https://midcoastsurf.com.au",
    "platform": "woocommerce",
    "regionCode": "AU",
    "enabled": false,
    "governanceStatus": "endpoint_review",
    "governanceReason": "No raw products returned from scrape output",
    "approvedLogoFile": "",
    "logoPath": "",
    "availableInventory": 0,
    "verifiedSurfboards": 0,
    "rawProducts": 0
  },
  {
    "retailerSlug": "red_herring_surf",
    "retailerName": "Red Herring Surf",
    "website": "https://redherringsurf.com.au",
    "platform": "shopify",
    "regionCode": "AU",
    "enabled": false,
    "governanceStatus": "endpoint_review",
    "governanceReason": "No raw products returned from scrape output",
    "approvedLogoFile": "",
    "logoPath": "",
    "availableInventory": 0,
    "verifiedSurfboards": 0,
    "rawProducts": 0
  },
  {
    "retailerSlug": "saltwater_wine_port_macquarie",
    "retailerName": "Saltwater Wine Port Macquarie",
    "website": "https://saltwaterwine.com.au",
    "platform": "shopify",
    "regionCode": "AU",
    "enabled": false,
    "governanceStatus": "endpoint_review",
    "governanceReason": "No raw products returned from scrape output",
    "approvedLogoFile": "",
    "logoPath": "",
    "availableInventory": 0,
    "verifiedSurfboards": 0,
    "rawProducts": 0
  },
  {
    "retailerSlug": "surf_shops_australia",
    "retailerName": "Surf Shops Australia",
    "website": "https://surfshopsaustralia.com.au",
    "platform": "bigcommerce",
    "regionCode": "AU",
    "enabled": false,
    "governanceStatus": "endpoint_review",
    "governanceReason": "No raw products returned from scrape output",
    "approvedLogoFile": "",
    "logoPath": "",
    "availableInventory": 0,
    "verifiedSurfboards": 0,
    "rawProducts": 0
  },
  {
    "retailerSlug": "surf_warehouse",
    "retailerName": "Surf Warehouse",
    "website": "https://surfwarehouse.com.au",
    "platform": "woocommerce",
    "regionCode": "AU",
    "enabled": false,
    "governanceStatus": "endpoint_review",
    "governanceReason": "No raw products returned from scrape output",
    "approvedLogoFile": "",
    "logoPath": "",
    "availableInventory": 0,
    "verifiedSurfboards": 0,
    "rawProducts": 0
  },
  {
    "retailerSlug": "trigger_bros_surfboards",
    "retailerName": "Trigger Bros Surfboards",
    "website": "https://triggerbrothers.com.au",
    "platform": "bigcommerce",
    "regionCode": "AU",
    "enabled": false,
    "governanceStatus": "endpoint_review",
    "governanceReason": "No raw products returned from scrape output",
    "approvedLogoFile": "",
    "logoPath": "",
    "availableInventory": 0,
    "verifiedSurfboards": 0,
    "rawProducts": 0
  },
  {
    "retailerSlug": "yallingup_surf_shop",
    "retailerName": "Yallingup Surf Shop",
    "website": "https://yallingupsurf.com.au",
    "platform": "woocommerce",
    "regionCode": "AU",
    "enabled": false,
    "governanceStatus": "endpoint_review",
    "governanceReason": "No raw products returned from scrape output",
    "approvedLogoFile": "",
    "logoPath": "",
    "availableInventory": 0,
    "verifiedSurfboards": 0,
    "rawProducts": 0
  },
  {
    "retailerSlug": "cordingleys_surf",
    "retailerName": "Cordingley's Surf",
    "website": "https://cordingleyssurf.com.au",
    "platform": "woocommerce",
    "regionCode": "AU",
    "enabled": false,
    "governanceStatus": "parser_review",
    "governanceReason": "Products scraped but surfboard filter did not identify boards",
    "approvedLogoFile": "",
    "logoPath": "",
    "availableInventory": 0,
    "verifiedSurfboards": 0,
    "rawProducts": 8
  },
  {
    "retailerSlug": "cronulla_surf_design",
    "retailerName": "Cronulla Surf Design",
    "website": "https://cronullasurfdesign.com.au",
    "platform": "shopify",
    "regionCode": "AU",
    "enabled": false,
    "governanceStatus": "parser_review",
    "governanceReason": "Products scraped but surfboard filter did not identify boards",
    "approvedLogoFile": "",
    "logoPath": "",
    "availableInventory": 0,
    "verifiedSurfboards": 0,
    "rawProducts": 363
  },
  {
    "retailerSlug": "empire_ave",
    "retailerName": "Empire Ave",
    "website": "https://empireave.com",
    "platform": "magento",
    "regionCode": "AU",
    "enabled": false,
    "governanceStatus": "parser_review",
    "governanceReason": "Products scraped but surfboard filter did not identify boards",
    "approvedLogoFile": "",
    "logoPath": "",
    "availableInventory": 0,
    "verifiedSurfboards": 0,
    "rawProducts": 30
  },
  {
    "retailerSlug": "island_surfboards",
    "retailerName": "Island Surfboards",
    "website": "https://islandsurfboards.com.au",
    "platform": "squarespace",
    "regionCode": "AU",
    "enabled": false,
    "governanceStatus": "parser_review",
    "governanceReason": "Products scraped but surfboard filter did not identify boards",
    "approvedLogoFile": "",
    "logoPath": "",
    "availableInventory": 0,
    "verifiedSurfboards": 0,
    "rawProducts": 128
  },
  {
    "retailerSlug": "manly_surf_guide_surfboard_outlet",
    "retailerName": "Manly Surf Guide Surfboard Outlet",
    "website": "https://manlysurfguide.com.au",
    "platform": "squarespace",
    "regionCode": "AU",
    "enabled": false,
    "governanceStatus": "parser_review",
    "governanceReason": "Products scraped but surfboard filter did not identify boards",
    "approvedLogoFile": "",
    "logoPath": "",
    "availableInventory": 0,
    "verifiedSurfboards": 0,
    "rawProducts": 15
  },
  {
    "retailerSlug": "slimes_boardstore",
    "retailerName": "Slimes Boardstore",
    "website": "",
    "platform": "ecwid",
    "regionCode": "AU",
    "enabled": false,
    "governanceStatus": "parser_review",
    "governanceReason": "Products scraped but surfboard filter did not identify boards",
    "approvedLogoFile": "",
    "logoPath": "",
    "availableInventory": 0,
    "verifiedSurfboards": 0,
    "rawProducts": 15
  },
  {
    "retailerSlug": "surf_boardroom",
    "retailerName": "Surf Boardroom",
    "website": "https://surfboardroom.com.au",
    "platform": "woocommerce",
    "regionCode": "AU",
    "enabled": false,
    "governanceStatus": "parser_review",
    "governanceReason": "Products scraped but surfboard filter did not identify boards",
    "approvedLogoFile": "",
    "logoPath": "",
    "availableInventory": 0,
    "verifiedSurfboards": 0,
    "rawProducts": 1
  },
  {
    "retailerSlug": "underground_surf",
    "retailerName": "Underground Surf",
    "website": "https://undergroundsurf.com.au",
    "platform": "shopify",
    "regionCode": "AU",
    "enabled": false,
    "governanceStatus": "parser_review",
    "governanceReason": "Products scraped but surfboard filter did not identify boards",
    "approvedLogoFile": "",
    "logoPath": "",
    "availableInventory": 0,
    "verifiedSurfboards": 0,
    "rawProducts": 163
  },
  {
    "retailerSlug": "surfboard_empire",
    "retailerName": "Surfboard Empire",
    "website": "https://surfboardempire.com.au",
    "platform": "shopify",
    "regionCode": "AU",
    "enabled": true,
    "governanceStatus": "production",
    "governanceReason": "Producing available surfboard inventory",
    "approvedLogoFile": "surfboard_empire.png",
    "logoPath": "/assets/retailers/surfboard_empire.png",
    "availableInventory": 4944,
    "verifiedSurfboards": 8589,
    "rawProducts": 17887
  },
  {
    "retailerSlug": "the_board_lab",
    "retailerName": "The Board Lab",
    "website": "https://theboardlab.com.au",
    "platform": "shopify",
    "regionCode": "AU",
    "enabled": true,
    "governanceStatus": "production",
    "governanceReason": "Producing available surfboard inventory",
    "approvedLogoFile": "the_board_lab.png",
    "logoPath": "/assets/retailers/the_board_lab.png",
    "availableInventory": 1438,
    "verifiedSurfboards": 2304,
    "rawProducts": 2952
  },
  {
    "retailerSlug": "wicks_surf",
    "retailerName": "Wicks Surf",
    "website": "https://wickssurf.com.au",
    "platform": "shopify",
    "regionCode": "AU",
    "enabled": true,
    "governanceStatus": "production",
    "governanceReason": "Producing available surfboard inventory",
    "approvedLogoFile": "wicks_surf.png",
    "logoPath": "/assets/retailers/wicks_surf.png",
    "availableInventory": 1420,
    "verifiedSurfboards": 1445,
    "rawProducts": 3034
  },
  {
    "retailerSlug": "natural_necessity",
    "retailerName": "Natural Necessity",
    "website": "https://naturalnecessity.com.au",
    "platform": "shopify",
    "regionCode": "AU",
    "enabled": true,
    "governanceStatus": "production",
    "governanceReason": "Producing available surfboard inventory",
    "approvedLogoFile": "natural_necessity.png",
    "logoPath": "/assets/retailers/natural_necessity.png",
    "availableInventory": 969,
    "verifiedSurfboards": 2262,
    "rawProducts": 33545
  },
  {
    "retailerSlug": "beachin_surf",
    "retailerName": "Beachin Surf",
    "website": "https://beachinsurf.com.au",
    "platform": "shopify",
    "regionCode": "AU",
    "enabled": true,
    "governanceStatus": "production",
    "governanceReason": "Producing available surfboard inventory",
    "approvedLogoFile": "beachin_surf.png",
    "logoPath": "/assets/retailers/beachin_surf.png",
    "availableInventory": 909,
    "verifiedSurfboards": 2793,
    "rawProducts": 47046
  },
  {
    "retailerSlug": "surf_culture_bondi",
    "retailerName": "Surf Culture Bondi",
    "website": "https://surfculture.com.au",
    "platform": "shopify",
    "regionCode": "AU",
    "enabled": true,
    "governanceStatus": "production",
    "governanceReason": "Producing available surfboard inventory",
    "approvedLogoFile": "surf_culture_bondi.png",
    "logoPath": "/assets/retailers/surf_culture_bondi.png",
    "availableInventory": 810,
    "verifiedSurfboards": 7197,
    "rawProducts": 15462
  },
  {
    "retailerSlug": "melbourne_surfboard_shop",
    "retailerName": "Melbourne Surfboard Shop",
    "website": "https://melbournesurfboardshop.com.au",
    "platform": "shopify",
    "regionCode": "AU",
    "enabled": true,
    "governanceStatus": "production",
    "governanceReason": "Producing available surfboard inventory",
    "approvedLogoFile": "melbourne_surfboard_shop.png",
    "logoPath": "/assets/retailers/melbourne_surfboard_shop.png",
    "availableInventory": 776,
    "verifiedSurfboards": 1074,
    "rawProducts": 4962
  },
  {
    "retailerSlug": "zink_surf",
    "retailerName": "Zink Surf",
    "website": "https://zinksurf.com.au",
    "platform": "shopify",
    "regionCode": "AU",
    "enabled": true,
    "governanceStatus": "production",
    "governanceReason": "Producing available surfboard inventory",
    "approvedLogoFile": "zink_surf.png",
    "logoPath": "/assets/retailers/zink_surf.png",
    "availableInventory": 610,
    "verifiedSurfboards": 623,
    "rawProducts": 1547
  },
  {
    "retailerSlug": "onboard_store",
    "retailerName": "Onboard Store",
    "website": "https://onboardstore.com.au",
    "platform": "shopify",
    "regionCode": "AU",
    "enabled": true,
    "governanceStatus": "production",
    "governanceReason": "Producing available surfboard inventory",
    "approvedLogoFile": "onboard_store.png",
    "logoPath": "/assets/retailers/onboard_store.png",
    "availableInventory": 603,
    "verifiedSurfboards": 603,
    "rawProducts": 2787
  },
  {
    "retailerSlug": "strapper_surf_torquay",
    "retailerName": "Strapper Surf Torquay",
    "website": "https://strapper.com.au",
    "platform": "woocommerce",
    "regionCode": "AU",
    "enabled": true,
    "governanceStatus": "production",
    "governanceReason": "Producing available surfboard inventory",
    "approvedLogoFile": "strapper_surf_torquay.png",
    "logoPath": "/assets/retailers/strapper_surf_torquay.png",
    "availableInventory": 561,
    "verifiedSurfboards": 561,
    "rawProducts": 3181
  },
  {
    "retailerSlug": "coopers_board_store",
    "retailerName": "Coopers Board Store",
    "website": "",
    "platform": "coopers, unknown",
    "regionCode": "AU",
    "enabled": true,
    "governanceStatus": "production",
    "governanceReason": "Producing available surfboard inventory",
    "approvedLogoFile": "coopers_board_store.png",
    "logoPath": "/assets/retailers/coopers_board_store.png",
    "availableInventory": 549,
    "verifiedSurfboards": 549,
    "rawProducts": 1156
  },
  {
    "retailerSlug": "sanbah_surf_shop",
    "retailerName": "Sanbah Surf Shop",
    "website": "https://sanbah.com",
    "platform": "shopify",
    "regionCode": "AU",
    "enabled": true,
    "governanceStatus": "production",
    "governanceReason": "Producing available surfboard inventory",
    "approvedLogoFile": "sanbah_surf_shop.png",
    "logoPath": "/assets/retailers/sanbah_surf_shop.png",
    "availableInventory": 494,
    "verifiedSurfboards": 3379,
    "rawProducts": 31356
  },
  {
    "retailerSlug": "sideways_surf",
    "retailerName": "Sideways Surf",
    "website": "https://sideways.com.au",
    "platform": "shopify",
    "regionCode": "AU",
    "enabled": true,
    "governanceStatus": "production",
    "governanceReason": "Producing available surfboard inventory",
    "approvedLogoFile": "sideways_surf.png",
    "logoPath": "/assets/retailers/sideways_surf.png",
    "availableInventory": 470,
    "verifiedSurfboards": 748,
    "rawProducts": 1256
  },
  {
    "retailerSlug": "classic_malibu",
    "retailerName": "Classic Malibu",
    "website": "https://classicmalibu.com",
    "platform": "woocommerce",
    "regionCode": "AU",
    "enabled": true,
    "governanceStatus": "production",
    "governanceReason": "Producing available surfboard inventory",
    "approvedLogoFile": "classic_malibu.png",
    "logoPath": "/assets/retailers/classic_malibu.png",
    "availableInventory": 462,
    "verifiedSurfboards": 475,
    "rawProducts": 868
  },
  {
    "retailerSlug": "slimes_newcastle",
    "retailerName": "Slimes Newcastle",
    "website": "https://www.slimesnewcastle.com.au",
    "platform": "shopify",
    "regionCode": "AU",
    "enabled": true,
    "governanceStatus": "production",
    "governanceReason": "Producing available surfboard inventory",
    "approvedLogoFile": "slimes_newcastle.png",
    "logoPath": "/assets/retailers/slimes_newcastle.png",
    "availableInventory": 438,
    "verifiedSurfboards": 6495,
    "rawProducts": 13068
  },
  {
    "retailerSlug": "aloha_surf_manly",
    "retailerName": "Aloha Surf Manly",
    "website": "https://alohasurfmanly.com",
    "platform": "neto_maropost",
    "regionCode": "AU",
    "enabled": true,
    "governanceStatus": "production",
    "governanceReason": "Producing available surfboard inventory",
    "approvedLogoFile": "aloha_surf_manly.png",
    "logoPath": "/assets/retailers/aloha_surf_manly.png",
    "availableInventory": 350,
    "verifiedSurfboards": 3449,
    "rawProducts": 2
  },
  {
    "retailerSlug": "star_surf_and_skate",
    "retailerName": "Star Surf and Skate",
    "website": "https://starsurf.com.au",
    "platform": "shopify",
    "regionCode": "AU",
    "enabled": true,
    "governanceStatus": "production",
    "governanceReason": "Producing available surfboard inventory",
    "approvedLogoFile": "star_surf_and_skate.png",
    "logoPath": "/assets/retailers/star_surf_and_skate.png",
    "availableInventory": 346,
    "verifiedSurfboards": 1105,
    "rawProducts": 13114
  },
  {
    "retailerSlug": "board_collective",
    "retailerName": "Board Collective",
    "website": "https://boardcollective.com.au",
    "platform": "shopify",
    "regionCode": "AU",
    "enabled": true,
    "governanceStatus": "production",
    "governanceReason": "Producing available surfboard inventory",
    "approvedLogoFile": "board_collective.png",
    "logoPath": "/assets/retailers/board_collective.png",
    "availableInventory": 292,
    "verifiedSurfboards": 635,
    "rawProducts": 27586
  },
  {
    "retailerSlug": "surfection_mosman",
    "retailerName": "Surfection Mosman",
    "website": "https://surfectionmosman.com",
    "platform": "shopify",
    "regionCode": "AU",
    "enabled": true,
    "governanceStatus": "production",
    "governanceReason": "Producing available surfboard inventory",
    "approvedLogoFile": "surfection_mosman.png",
    "logoPath": "/assets/retailers/surfection_mosman.png",
    "availableInventory": 264,
    "verifiedSurfboards": 264,
    "rawProducts": 270
  },
  {
    "retailerSlug": "powerhouse_surf",
    "retailerName": "Powerhouse Surf",
    "website": "https://powerhousesurf.com.au",
    "platform": "shopify",
    "regionCode": "AU",
    "enabled": true,
    "governanceStatus": "production",
    "governanceReason": "Producing available surfboard inventory",
    "approvedLogoFile": "powerhouse_surf.png",
    "logoPath": "/assets/retailers/powerhouse_surf.png",
    "availableInventory": 210,
    "verifiedSurfboards": 1961,
    "rawProducts": 15623
  },
  {
    "retailerSlug": "the_surfboard_warehouse",
    "retailerName": "The Surfboard Warehouse",
    "website": "https://thesurfboardwarehouse.com.au",
    "platform": "shopify",
    "regionCode": "AU",
    "enabled": true,
    "governanceStatus": "production",
    "governanceReason": "Producing available surfboard inventory",
    "approvedLogoFile": "the_surfboard_warehouse.png",
    "logoPath": "/assets/retailers/the_surfboard_warehouse.png",
    "availableInventory": 185,
    "verifiedSurfboards": 248,
    "rawProducts": 726
  },
  {
    "retailerSlug": "surfection_bondi",
    "retailerName": "Surfection Bondi",
    "website": "https://surfection.com",
    "platform": "shopify",
    "regionCode": "AU",
    "enabled": true,
    "governanceStatus": "production",
    "governanceReason": "Producing available surfboard inventory",
    "approvedLogoFile": "surfection_bondi.png",
    "logoPath": "/assets/retailers/surfection_bondi.png",
    "availableInventory": 166,
    "verifiedSurfboards": 1174,
    "rawProducts": 2970
  },
  {
    "retailerSlug": "boards_in_the_bay",
    "retailerName": "Boards In The Bay",
    "website": "https://boardsinthebay.com.au",
    "platform": "shopify",
    "regionCode": "AU",
    "enabled": true,
    "governanceStatus": "production",
    "governanceReason": "Producing available surfboard inventory",
    "approvedLogoFile": "boards_in_the_bay.png",
    "logoPath": "/assets/retailers/boards_in_the_bay.png",
    "availableInventory": 150,
    "verifiedSurfboards": 688,
    "rawProducts": 3034
  },
  {
    "retailerSlug": "noosa_longboards",
    "retailerName": "Noosa Longboards",
    "website": "https://noosalongboards.com",
    "platform": "shopify",
    "regionCode": "AU",
    "enabled": true,
    "governanceStatus": "production",
    "governanceReason": "Producing available surfboard inventory",
    "approvedLogoFile": "noosa_longboards.png",
    "logoPath": "/assets/retailers/noosa_longboards.png",
    "availableInventory": 150,
    "verifiedSurfboards": 160,
    "rawProducts": 2758
  },
  {
    "retailerSlug": "nt_surfboards",
    "retailerName": "NT Surfboards",
    "website": "https://ntsurfboards.com",
    "platform": "shopify",
    "regionCode": "AU",
    "enabled": true,
    "governanceStatus": "production",
    "governanceReason": "Producing available surfboard inventory",
    "approvedLogoFile": "nt_surfboards.png",
    "logoPath": "/assets/retailers/nt_surfboards.png",
    "availableInventory": 123,
    "verifiedSurfboards": 124,
    "rawProducts": 125
  },
  {
    "retailerSlug": "anglesea_surf_centre",
    "retailerName": "Anglesea Surf Centre",
    "website": "https://angleseasurfcentre.com.au",
    "platform": "woocommerce",
    "regionCode": "AU",
    "enabled": true,
    "governanceStatus": "production",
    "governanceReason": "Producing available surfboard inventory",
    "approvedLogoFile": "anglesea_surf_centre.png",
    "logoPath": "/assets/retailers/anglesea_surf_centre.png",
    "availableInventory": 97,
    "verifiedSurfboards": 97,
    "rawProducts": 99
  },
  {
    "retailerSlug": "long_reef_surf_co",
    "retailerName": "Long Reef Surf Co",
    "website": "https://longreefsurf.com.au",
    "platform": "shopify",
    "regionCode": "AU",
    "enabled": true,
    "governanceStatus": "production",
    "governanceReason": "Producing available surfboard inventory",
    "approvedLogoFile": "long_reef_surf_co.png",
    "logoPath": "/assets/retailers/long_reef_surf_co.png",
    "availableInventory": 92,
    "verifiedSurfboards": 298,
    "rawProducts": 10481
  },
  {
    "retailerSlug": "extreme_boardriders",
    "retailerName": "Extreme Boardriders",
    "website": "https://extremeboardriders.com.au",
    "platform": "woocommerce",
    "regionCode": "AU",
    "enabled": true,
    "governanceStatus": "production",
    "governanceReason": "Producing available surfboard inventory",
    "approvedLogoFile": "extreme_boardriders.png",
    "logoPath": "/assets/retailers/extreme_boardriders.png",
    "availableInventory": 47,
    "verifiedSurfboards": 47,
    "rawProducts": 145
  },
  {
    "retailerSlug": "manly_surfboards",
    "retailerName": "Manly Surfboards",
    "website": "https://manlysurfboards.com.au",
    "platform": "woocommerce",
    "regionCode": "AU",
    "enabled": true,
    "governanceStatus": "production",
    "governanceReason": "Producing available surfboard inventory",
    "approvedLogoFile": "manly_surfboards.png",
    "logoPath": "/assets/retailers/manly_surfboards.png",
    "availableInventory": 47,
    "verifiedSurfboards": 1987,
    "rawProducts": 7055
  },
  {
    "retailerSlug": "ocean_addicts",
    "retailerName": "Ocean Addicts",
    "website": "https://oceanaddicts.com.au",
    "platform": "woocommerce",
    "regionCode": "AU",
    "enabled": true,
    "governanceStatus": "production",
    "governanceReason": "Producing available surfboard inventory",
    "approvedLogoFile": "ocean_addicts.png",
    "logoPath": "/assets/retailers/ocean_addicts.png",
    "availableInventory": 41,
    "verifiedSurfboards": 41,
    "rawProducts": 311
  },
  {
    "retailerSlug": "surf_fx",
    "retailerName": "Surf FX",
    "website": "https://surffx.com.au",
    "platform": "shopify",
    "regionCode": "AU",
    "enabled": true,
    "governanceStatus": "production",
    "governanceReason": "Producing available surfboard inventory",
    "approvedLogoFile": "surf_fx.png",
    "logoPath": "/assets/retailers/surf_fx.png",
    "availableInventory": 33,
    "verifiedSurfboards": 166,
    "rawProducts": 5254
  },
  {
    "retailerSlug": "the_surfboard_studio",
    "retailerName": "The Surfboard Studio",
    "website": "https://thesurfboardstudio.com.au",
    "platform": "shopify",
    "regionCode": "AU",
    "enabled": true,
    "governanceStatus": "production",
    "governanceReason": "Producing available surfboard inventory",
    "approvedLogoFile": "the_surfboard_studio.png",
    "logoPath": "/assets/retailers/the_surfboard_studio.png",
    "availableInventory": 8,
    "verifiedSurfboards": 43,
    "rawProducts": 1459
  },
  {
    "retailerSlug": "beach_beat_alexandra_headland",
    "retailerName": "Beach Beat Alexandra Headland",
    "website": "https://beachbeat.com.au",
    "platform": "woocommerce",
    "regionCode": "AU",
    "enabled": true,
    "governanceStatus": "production",
    "governanceReason": "Producing available surfboard inventory",
    "approvedLogoFile": "beach_beat_alexandra_headland.png",
    "logoPath": "/assets/retailers/beach_beat_alexandra_headland.png",
    "availableInventory": 7,
    "verifiedSurfboards": 7,
    "rawProducts": 19
  },
  {
    "retailerSlug": "akwa_surf",
    "retailerName": "Akwa Surf",
    "website": "https://akwasurf.com.au",
    "platform": "shopify",
    "regionCode": "AU",
    "enabled": true,
    "governanceStatus": "production",
    "governanceReason": "Producing available surfboard inventory",
    "approvedLogoFile": "akwa_surf.png",
    "logoPath": "/assets/retailers/akwa_surf.png",
    "availableInventory": 6,
    "verifiedSurfboards": 65,
    "rawProducts": 2793
  },
  {
    "retailerSlug": "awsm_surf",
    "retailerName": "AWSM Surf",
    "website": "https://awsmsurf.com",
    "platform": "shopify",
    "regionCode": "AU",
    "enabled": false,
    "governanceStatus": "stock_status_review",
    "governanceReason": "Surfboards identified but no available inventory",
    "approvedLogoFile": "",
    "logoPath": "",
    "availableInventory": 0,
    "verifiedSurfboards": 3,
    "rawProducts": 1966
  },
  {
    "retailerSlug": "overboard_surf",
    "retailerName": "Overboard Surf",
    "website": "https://overboardsurf.com.au",
    "platform": "shopify",
    "regionCode": "AU",
    "enabled": false,
    "governanceStatus": "stock_status_review",
    "governanceReason": "Surfboards identified but no available inventory",
    "approvedLogoFile": "",
    "logoPath": "",
    "availableInventory": 0,
    "verifiedSurfboards": 278,
    "rawProducts": 1300
  }
]