[
  {
    "title": "#77",
    "handle": "77",
    "product_type": "",
    "tags": [
      "#77",
      "full range",
      "master",
      "pro range"
    ],
    "variants": [
      {
        "title": "Default Title",
        "sku": "",
        "price": "760.00",
        "available": false
      }
    ]
  },
  {
    "title": "#77 (E3 LITE)",
    "handle": "77-e3-lite",
    "product_type": "",
    "tags": [
      "E3-EPS",
      "E3-EPS range",
      "E3-Lite",
      "full range",
      "master",
      "pro range"
    ],
    "variants": [
      {
        "title": "Default Title",
        "sku": "",
        "price": "825.00",
        "available": false
      }
    ]
  },
  {
    "title": "CHEAT CODE  (E3 LITE)",
    "handle": "cheat-code-e3-lite",
    "product_type": "Shortboard",
    "tags": [
      "alternate range",
      "E3-EPS",
      "E3-EPS range",
      "E3-Lite",
      "full range",
      "master",
      "performance range"
    ],
    "variants": [
      {
        "title": "FCS 2 / 5'4\" X 19\" X 2.37\" X 25.6L / Dark Grey Rail",
        "sku": "",
        "price": "825.00",
        "available": true
      },
      {
        "title": "FCS 2 / 5'4\" X 19\" X 2.37\" X 25.6L / Bright Blue Rail",
        "sku": "",
        "price": "825.00",
        "available": true
      },
      {
        "title": "FCS 2 / 5'6\" X 19.37\" X 2.37\" X 27L / Dark Grey Rail",
        "sku": "",
        "price": "825.00",
        "available": true
      },
      {
        "title": "FCS 2 / 5'6\" X 19.37\" X 2.37\" X 27L / Bright Blue Rail",
        "sku": "",
        "price": "825.00",
        "available": true
      },
      {
        "title": "FCS 2 / 5'8\" X 19.5\" X 2.43\" X 28.6L / Dark Grey Rail",
        "sku": "",
        "price": "825.00",
        "available": false
      },
      {
        "title": "FCS 2 / 5'8\" X 19.5\" X 2.43\" X 28.6L / Bright Blue Rail",
        "sku": "",
        "price": "825.00",
        "available": true
      },
      {
        "title": "FCS 2 / 5'8\" HV X 20\" X 2.65\" X 32.6L / Dark Grey Rail",
        "sku": "",
        "price": "825.00",
        "available": true
      },
      {
        "title": "FCS 2 / 5'8\" HV X 20\" X 2.65\" X 32.6L / Bright Blue Rail",
        "sku": "",
        "price": "825.00",
        "available": true
      },
      {
        "title": "FCS 2 / 5'9\" x 19.5\" x 2.5\" x 30L / Dark Grey Rail",
        "sku": "",
        "price": "825.00",
        "available": true
      },
      {
        "title": "FCS 2 / 5'9\" x 19.5\" x 2.5\" x 30L / Bright Blue Rail",
        "sku": "",
        "price": "825.00",
        "available": false
      },
      {
        "title": "FCS 2 / 5'10\" x 19.75\" x 2.55\" x 31.3L / Dark Grey Rail",
        "sku": "",
        "price": "825.00",
        "available": true
      },
      {
        "title": "FCS 2 / 5'10\" x 19.75\" x 2.55\" x 31.3L / Bright Blue Rail",
        "sku": "",
        "price": "825.00",
        "available": true
      },
      {
        "title": "FCS 2 / 5'10\" HV x 20.75\" x 2.75\" x 35.8L / Dark Grey Rail",
        "sku": "",
        "price": "825.00",
        "available": false
      },
      {
        "title": "FCS 2 / 5'10\" HV x 20.75\" x 2.75\" x 35.8L / Bright Blue Rail",
        "sku": "",
        "price": "825.00",
        "available": true
      },
      {
        "title": "FCS 2 / 6'0\" x 20\" x 2.62\" x 33.9L / Dark Grey Rail",
        "sku": "",
        "price": "825.00",
        "available": true
      },
      {
        "title": "FCS 2 / 6'0\" x 20\" x 2.62\" x 33.9L / Bright Blue Rail",
        "sku": "",
        "price": "825.00",
        "available": true
      },
      {
        "title": "FCS 2 / 6'0\" HV x 21\" x 2.85\"  x 38.6L / Dark Grey Rail",
        "sku": "",
        "price": "825.00",
        "available": true
      },
      {
        "title": "FCS 2 / 6'0\" HV x 21\" x 2.85\"  x 38.6L / Bright Blue Rail",
        "sku": "",
        "price": "825.00",
        "available": true
      },
      {
        "title": "FCS 2 / 6'2\" x 20.5\" x 2.68\" x 36.9L / Dark Grey Rail",
        "sku": "",
        "price": "825.00",
        "available": true
      },
      {
        "title": "FCS 2 / 6'2\" x 20.5\" x 2.68\" x 36.9L / Bright Blue Rail",
        "sku": "",
        "price": "825.00",
        "available": true
      },
      {
        "title": "FCS 2 / 6'4\" x 20.75\" x 2.75\" x 38.5L / Dark Grey Rail",
        "sku": "",
        "price": "825.00",
        "available": true
      },
      {
        "title": "FCS 2 / 6'4\" x 20.75\" x 2.75\" x 38.5L / Bright Blue Rail",
        "sku": "",
        "price": "825.00",
        "available": true
      },
      {
        "title": "FCS 2 / 6'6\" x 21\" x 2.87\" x 42.1L / Dark Grey Rail",
        "sku": "",
        "price": "825.00",
        "available": true
      },
      {
        "title": "FCS 2 / 6'6\" x 21\" x 2.87\" x 42.1L / Bright Blue Rail",
        "sku": "",
        "price": "825.00",
        "available": true
      },
      {
        "title": "Futures / 5'4\" X 19\" X 2.37\" X 25.6L / Dark Grey Rail",
        "sku": "",
        "price": "825.00",
        "available": true
      },
      {
        "title": "Futures / 5'4\" X 19\" X 2.37\" X 25.6L / Bright Blue Rail",
        "sku": "",
        "price": "825.00",
        "available": false
      },
      {
        "title": "Futures / 5'6\" X 19.37\" X 2.37\" X 27L / Dark Grey Rail",
        "sku": "",
        "price": "825.00",
        "available": true
      },
      {
        "title": "Futures / 5'6\" X 19.37\" X 2.37\" X 27L / Bright Blue Rail",
        "sku": "",
        "price": "825.00",
        "available": false
      },
      {
        "title": "Futures / 5'8\" X 19.5\" X 2.43\" X 28.6L / Dark Grey Rail",
        "sku": "",
        "price": "825.00",
        "available": true
      },
      {
        "title": "Futures / 5'8\" X 19.5\" X 2.43\" X 28.6L / Bright Blue Rail",
        "sku": "",
        "price": "825.00",
        "available": true
      },
      {
        "title": "Futures / 5'8\" HV X 20\" X 2.65\" X 32.6L / Dark Grey Rail",
        "sku": "",
        "price": "825.00",
        "available": true
      },
      {
        "title": "Futures / 5'8\" HV X 20\" X 2.65\" X 32.6L / Bright Blue Rail",
        "sku": "",
        "price": "825.00",
        "available": true
      },
      {
        "title": "Futures / 5'9\" x 19.5\" x 2.5\" x 30L / Dark Grey Rail",
        "sku": "",
        "price": "825.00",
        "available": true
      },
      {
        "title": "Futures / 5'9\" x 19.5\" x 2.5\" x 30L / Bright Blue Rail",
        "sku": "",
        "price": "825.00",
        "available": true
      },
      {
        "title": "Futures / 5'10\" x 19.75\" x 2.55\" x 31.3L / Dark Grey Rail",
        "sku": "",
        "price": "825.00",
        "available": true
      },
      {
        "title": "Futures / 5'10\" x 19.75\" x 2.55\" x 31.3L / Bright Blue Rail",
        "sku": "",
        "price": "825.00",
        "available": true
      },
      {
        "title": "Futures / 5'10\" HV x 20.75\" x 2.75\" x 35.8L / Dark Grey Rail",
        "sku": "",
        "price": "825.00",
        "available": true
      },
      {
        "title": "Futures / 5'10\" HV x 20.75\" x 2.75\" x 35.8L / Bright Blue Rail",
        "sku": "",
        "price": "825.00",
        "available": true
      },
      {
        "title": "Futures / 6'0\" x 20\" x 2.62\" x 33.9L / Dark Grey Rail",
        "sku": "",
        "price": "825.00",
        "available": true
      },
      {
        "title": "Futures / 6'0\" x 20\" x 2.62\" x 33.9L / Bright Blue Rail",
        "sku": "",
        "price": "825.00",
        "available": true
      },
      {
        "title": "Futures / 6'0\" HV x 21\" x 2.85\"  x 38.6L / Dark Grey Rail",
        "sku": "",
        "price": "825.00",
        "available": true
      },
      {
        "title": "Futures / 6'0\" HV x 21\" x 2.85\"  x 38.6L / Bright Blue Rail",
        "sku": "",
        "price": "825.00",
        "available": true
      },
      {
        "title": "Futures / 6'2\" x 20.5\" x 2.68\" x 36.9L / Dark Grey Rail",
        "sku": "",
        "price": "825.00",
        "available": true
      },
      {
        "title": "Futures / 6'2\" x 20.5\" x 2.68\" x 36.9L / Bright Blue Rail",
        "sku": "",
        "price": "825.00",
        "available": false
      },
      {
        "title": "Futures / 6'4\" x 20.75\" x 2.75\" x 38.5L / Dark Grey Rail",
        "sku": "",
        "price": "825.00",
        "available": false
      },
      {
        "title": "Futures / 6'4\" x 20.75\" x 2.75\" x 38.5L / Bright Blue Rail",
        "sku": "",
        "price": "825.00",
        "available": false
      },
      {
        "title": "Futures / 6'6\" x 21\" x 2.87\" x 42.1L / Dark Grey Rail",
        "sku": "",
        "price": "825.00",
        "available": true
      },
      {
        "title": "Futures / 6'6\" x 21\" x 2.87\" x 42.1L / Bright Blue Rail",
        "sku": "",
        "price": "825.00",
        "available": false
      }
    ]
  },
  {
    "title": "CHEAT CODE",
    "handle": "cheater",
    "product_type": "",
    "tags": [
      "alternate range",
      "Cheat Code",
      "e3",
      "full range",
      "master",
      "performance range"
    ],
    "variants": [
      {
        "title": "Default Title",
        "sku": "",
        "price": "760.00",
        "available": false
      }
    ]
  },
  {
    "title": "CHEAT CODE (C1 LITE)",
    "handle": "copy-of-twin-turbo-c1-lite",
    "product_type": "",
    "tags": [
      "alternate range",
      "c1 carbon range",
      "c1-carbon",
      "CHEAT CODE (C1 LITE)",
      "full range",
      "master",
      "performance range"
    ],
    "variants": [
      {
        "title": "Default Title",
        "sku": null,
        "price": "799.00",
        "available": false
      }
    ]
  },
  {
    "title": "DISCO",
    "handle": "disco",
    "product_type": "",
    "tags": [
      "Disco",
      "full range",
      "master",
      "performance-range"
    ],
    "variants": [
      {
        "title": "Default Title",
        "sku": "",
        "price": "760.00",
        "available": false
      }
    ]
  },
  {
    "title": "DISCO II (E3 LITE)",
    "handle": "disco-ii",
    "product_type": "",
    "tags": [
      "E3-EPS",
      "E3-EPS range",
      "E3-Lite",
      "full range",
      "master",
      "performance range"
    ],
    "variants": [
      {
        "title": "Default Title",
        "sku": "",
        "price": "825.00",
        "available": false
      }
    ]
  },
  {
    "title": "DISCO II",
    "handle": "disco-ii-1",
    "product_type": "",
    "tags": [
      "full range",
      "master",
      "performance range"
    ],
    "variants": [
      {
        "title": "Default Title",
        "sku": "",
        "price": "760.00",
        "available": false
      }
    ]
  },
  {
    "title": "DISCO II (C1 LITE)",
    "handle": "disco-ii-c1-lite",
    "product_type": "",
    "tags": [
      "c1 carbon range",
      "c1-carbon",
      "full range",
      "master",
      "performance range"
    ],
    "variants": [
      {
        "title": "Default Title",
        "sku": "",
        "price": "999.00",
        "available": false
      }
    ]
  },
  {
    "title": "DISCO INFERNO",
    "handle": "disco-inferno",
    "product_type": "",
    "tags": [
      "Disco Inferno",
      "full range",
      "master",
      "performance range"
    ],
    "variants": [
      {
        "title": "Default Title",
        "sku": "",
        "price": "760.00",
        "available": false
      }
    ]
  },
  {
    "title": "FILE FIFTY",
    "handle": "file-fifty",
    "product_type": "",
    "tags": [
      "full range",
      "master",
      "performance range"
    ],
    "variants": [
      {
        "title": "Default Title",
        "sku": "",
        "price": "760.00",
        "available": false
      }
    ]
  },
  {
    "title": "FILE FIFTY (E3 LITE)",
    "handle": "file-fifty-e3-lite",
    "product_type": "",
    "tags": [
      "E3-EPS",
      "E3-EPS range",
      "E3-Lite",
      "full range",
      "master",
      "performance range"
    ],
    "variants": [
      {
        "title": "Default Title",
        "sku": "",
        "price": "825.00",
        "available": false
      }
    ]
  },
  {
    "title": "HOLY TOLEDO",
    "handle": "holy-toledo",
    "product_type": "",
    "tags": [
      "full range",
      "Holy Toledo",
      "master",
      "pro range"
    ],
    "variants": [
      {
        "title": "Default Title",
        "sku": "",
        "price": "760.00",
        "available": false
      }
    ]
  },
  {
    "title": "HT2",
    "handle": "ht2",
    "product_type": "",
    "tags": [
      "e3",
      "full range",
      "HT2",
      "master",
      "pro range"
    ],
    "variants": [
      {
        "title": "Default Title",
        "sku": "",
        "price": "760.00",
        "available": false
      }
    ]
  },
  {
    "title": "HT2.5",
    "handle": "ht2-5",
    "product_type": "",
    "tags": [
      "full range",
      "HT2.5",
      "master",
      "pro range"
    ],
    "variants": [
      {
        "title": "Default Title",
        "sku": "",
        "price": "770.00",
        "available": false
      }
    ]
  },
  {
    "title": "HT2 YTH",
    "handle": "ht2-youth",
    "product_type": "",
    "tags": [
      "full range",
      "HT2 Youth",
      "master",
      "pro range",
      "youth range"
    ],
    "variants": [
      {
        "title": "Default Title",
        "sku": "",
        "price": "679.00",
        "available": false
      }
    ]
  },
  {
    "title": "SB-1",
    "handle": "inferno-72",
    "product_type": "",
    "tags": [
      "full range",
      "master",
      "performance range",
      "SB-1"
    ],
    "variants": [
      {
        "title": "Default Title",
        "sku": "",
        "price": "760.00",
        "available": false
      }
    ]
  },
  {
    "title": "INFERNO 72 (E3 LITE)",
    "handle": "inferno-72-e3-lite-1",
    "product_type": "",
    "tags": [
      "E3-EPS",
      "E3-EPS range",
      "E3-Lite",
      "full range",
      "master",
      "performance range"
    ],
    "variants": [
      {
        "title": "Default Title",
        "sku": "",
        "price": "825.00",
        "available": false
      }
    ]
  },
  {
    "title": "INFERNO 72 YTH",
    "handle": "inferno-72-yth",
    "product_type": "",
    "tags": [
      "full range",
      "Inferno 72 Youth",
      "master",
      "performance range",
      "youth range"
    ],
    "variants": [
      {
        "title": "Default Title",
        "sku": "",
        "price": "679.00",
        "available": true
      }
    ]
  },
  {
    "title": "INFERNO 72",
    "handle": "inferno-73",
    "product_type": "",
    "tags": [
      "e3",
      "full range",
      "Inferno 72",
      "master",
      "performance range"
    ],
    "variants": [
      {
        "title": "Default Title",
        "sku": "",
        "price": "760.00",
        "available": false
      }
    ]
  },
  {
    "title": "INFERNO FT",
    "handle": "inferno-ft",
    "product_type": "",
    "tags": [
      "full range",
      "Inferno FT",
      "master",
      "pro range"
    ],
    "variants": [
      {
        "title": "Default Title",
        "sku": "",
        "price": "780.00",
        "available": false
      }
    ]
  },
  {
    "title": "INFERNO FT (E3 LITE)",
    "handle": "inferno-ft-e3-lite",
    "product_type": "",
    "tags": [
      "E3-EPS",
      "E3-EPS range",
      "E3-Lite",
      "full range",
      "master",
      "pro range"
    ],
    "variants": [
      {
        "title": "Default Title",
        "sku": null,
        "price": "825.00",
        "available": false
      }
    ]
  },
  {
    "title": "MAGURO",
    "handle": "maguro",
    "product_type": "",
    "tags": [
      "alternate range",
      "full range",
      "Maguro",
      "master"
    ],
    "variants": [
      {
        "title": "Default Title",
        "sku": "",
        "price": "760.00",
        "available": false
      }
    ]
  },
  {
    "title": "MIDGICIAN",
    "handle": "midgician",
    "product_type": "",
    "tags": [
      "alternate range",
      "full range",
      "master"
    ],
    "variants": [
      {
        "title": "Default Title",
        "sku": "",
        "price": "840.00",
        "available": false
      }
    ]
  },
  {
    "title": "MIDGICIAN (E3 LITE)",
    "handle": "midgician-e3-lite",
    "product_type": "",
    "tags": [
      "alternate range",
      "E3-EPS",
      "E3-EPS range",
      "E3-Lite",
      "full range",
      "master"
    ],
    "variants": [
      {
        "title": "Default Title",
        "sku": "",
        "price": "895.00",
        "available": false
      }
    ]
  },
  {
    "title": "MODERN 2",
    "handle": "modern-2",
    "product_type": "",
    "tags": [
      "alternate range",
      "e3",
      "full range",
      "master",
      "Modern 2"
    ],
    "variants": [
      {
        "title": "Default Title",
        "sku": "",
        "price": "760.00",
        "available": false
      }
    ]
  },
  {
    "title": "MODERN 2.5",
    "handle": "modern-2-5",
    "product_type": "",
    "tags": [
      "alternate range",
      "e3",
      "full range",
      "master",
      "Modern 2.5"
    ],
    "variants": [
      {
        "title": "Default Title",
        "sku": "",
        "price": "760.00",
        "available": false
      }
    ]
  },
  {
    "title": "MODERN 2 (E3-LITE)",
    "handle": "modern-2-e3-lite",
    "product_type": "",
    "tags": [
      "alternate range",
      "E3-EPS",
      "E3-EPS range",
      "E3-Lite",
      "full range",
      "master"
    ],
    "variants": [
      {
        "title": "Default Title",
        "sku": "",
        "price": "825.00",
        "available": false
      }
    ]
  },
  {
    "title": "OKAY",
    "handle": "okay",
    "product_type": "",
    "tags": [
      "full range",
      "master",
      "OKAY",
      "performance range"
    ],
    "variants": [
      {
        "title": "Default Title",
        "sku": "",
        "price": "760.00",
        "available": false
      }
    ]
  },
  {
    "title": "RADAR",
    "handle": "radar",
    "product_type": "",
    "tags": [
      "alternate range",
      "full range",
      "master"
    ],
    "variants": [
      {
        "title": "Default Title",
        "sku": null,
        "price": "760.00",
        "available": false
      }
    ]
  },
  {
    "title": "STORMS",
    "handle": "storms",
    "product_type": "",
    "tags": [
      "full range",
      "master",
      "performance range",
      "Storms"
    ],
    "variants": [
      {
        "title": "Default Title",
        "sku": "",
        "price": "780.00",
        "available": false
      }
    ]
  },
  {
    "title": "TWIN TURBO",
    "handle": "storms-t2",
    "product_type": "",
    "tags": [
      "alternate range",
      "e3",
      "full range",
      "master",
      "Storms T2",
      "Twin Turbo"
    ],
    "variants": [
      {
        "title": "Default Title",
        "sku": "",
        "price": "780.00",
        "available": false
      }
    ]
  },
  {
    "title": "TWIN TURBO (E3 LITE)",
    "handle": "storms-t2-e3-lite",
    "product_type": "",
    "tags": [
      "alternate range",
      "E3-EPS",
      "E3-EPS range",
      "E3-Lite",
      "full range",
      "master"
    ],
    "variants": [
      {
        "title": "Default Title",
        "sku": "",
        "price": "825.00",
        "available": false
      }
    ]
  },
  {
    "title": "SYNERGY",
    "handle": "synergy",
    "product_type": "",
    "tags": [
      "full range",
      "master",
      "performance range",
      "se store"
    ],
    "variants": [
      {
        "title": "Default Title",
        "sku": "",
        "price": "760.00",
        "available": false
      }
    ]
  },
  {
    "title": "SYNERGY YTH",
    "handle": "synergy-yth",
    "product_type": "",
    "tags": [
      "full range",
      "master",
      "performance range",
      "Synergy Youth",
      "youth range"
    ],
    "variants": [
      {
        "title": "Default Title",
        "sku": "",
        "price": "679.00",
        "available": true
      }
    ]
  },
  {
    "title": "TWIN TURBO (C1 LITE)",
    "handle": "twin-turbo-c1-lite",
    "product_type": "",
    "tags": [
      "alternate range",
      "c1 carbon range",
      "c1-carbon",
      "full range",
      "master",
      "Storms T2",
      "Twin Turbo"
    ],
    "variants": [
      {
        "title": "Default Title",
        "sku": "",
        "price": "999.00",
        "available": false
      }
    ]
  },
  {
    "title": "ZIPPER (E3 LITE)",
    "handle": "zipper",
    "product_type": "",
    "tags": [
      "alternate range",
      "E3-EPS",
      "E3-EPS range",
      "E3-Lite",
      "full range",
      "master"
    ],
    "variants": [
      {
        "title": "Default Title",
        "sku": "",
        "price": "850.00",
        "available": false
      }
    ]
  },
  {
    "title": "ZIPPER",
    "handle": "zipper-1",
    "product_type": "",
    "tags": [
      "alternate range",
      "full range",
      "master"
    ],
    "variants": [
      {
        "title": "Default Title",
        "sku": "",
        "price": "760.00",
        "available": false
      }
    ]
  }
]